sequential_circuits/basic_storage_elements/sr_latch.v
module sr_latch(
    input wire s,r,  //s=set and r=reset
    output wire q,nq //q=Q and nq=~Q
);         //NOR BASED-ACTIVE HIGH S/R 
nor g1(q,r,nq);
nor g2(nq,s,q);         //idle state s=r=0 = hold
endmodule


module sr_latch_nand(
    input wire s_n,r_n,  //NAND BASED-ACTIVE LOW S/R
    output wire q,nq
);                              //idle state s_n=r_n = 1 = hold
nand g1(q,s_n,nq);
nand g2(nq,r_n,q);       //more prefered in standard cell libraries typically faster & smaller than nor
endmodule

module sr_latch_behavioral(
    input s,r,en,            //gated sr latch used so we dont have race condition s=r=1
    output reg q,
    output qn    //no reg for this one beacuse it doesnt drive input 
);
                                     //synthesizable
always @(*) begin
    if (en) begin
        if (s && !r) q=1'b1;
        else if (!s && r) q=1'b0;
        else if (s && r) q=1'bx;      //no if else intended latch we want but for diiferent ff must use if else at last
    end  // s=0,r=0 → q retains old value (this is what infers the latch)
end     // en=0 → q retains old value too — intentional level-sensitive latch
assign qn = ~q;
endmodule

//DATAFLOW ONLY GOOD FOR SIMULATION DIRECT BOOLEAN EXPRESSION

sequential_circuits/tb/tb_sr_latch.v
module tb_sr_latch;

reg s, r, en;
wire q, qn;
reg exp_q;
integer errors;

sr_latch_behavioral uut (.s(s), .r(r), .en(en), .q(q), .qn(qn));

initial begin 
    errors = 0;
    $dumpfile("srlatch.vcd");
    $dumpvars(0, tb_sr_latch);

    en=1; s=0; r=1; #10; exp_q=0; check(exp_q);
          s=1; r=0; #10; exp_q=1; check(exp_q);
          s=0; r=0; #10; check(exp_q);

    en=0; #5;  
    s=1; r=0; #10; check(exp_q);
    en=1; #10; exp_q=1; check(exp_q); 
    s=0; r=1; #10; exp_q=0; check(exp_q);

    s = 1; r = 1; #10;
    if (q !== 1'bx) begin
        $display("FAIL: forbidden state S=R=1 did not produce X, got %b", q);
        errors = errors + 1;
    end

    if (errors == 0) $display("ALL TESTS PASSED");
    else              $display("FAILED: %0d errors", errors);
    $finish;
end   

task automatic check;
    input expected;
    if (q !== expected) begin
        $display("FAIL: s=%b r=%b en=%b expected q=%b got q=%b",
                  s, r, en, expected, q);
        errors = errors + 1;
    end
endtask

endmodule

sequential_circuits/sim/srlatch.vcd
$date
	Wed Aug 26 13:25:59 2026
$end
$version
	Icarus Verilog
$end
$timescale
	1s
$end
$scope module tb_sr_latch $end
$var wire 1 ! qn $end
$var wire 1 " q $end
$var reg 1 # en $end
$var reg 1 $ exp_q $end
$var reg 1 % r $end
$var reg 1 & s $end
$var integer 32 ' errors [31:0] $end
$scope module uut $end
$var wire 1 # en $end
$var wire 1 ! qn $end
$var wire 1 % r $end
$var wire 1 & s $end
$var reg 1 " q $end
$upscope $end
$scope task check $end
$upscope $end
$upscope $end
$enddefinitions $end
$comment Show the parameter values. $end
$dumpall
$end
#0
$dumpvars
b0 '
0&
1%
x$
1#
0"
1!
$end
#10
0!
1"
0%
1&
0$
#20
0&
1$
#30
0#
#35
1&
#45
1#
#55
1!
0"
1%
0&
#65
x!
x"
1&
0$
